<?xml version="1.0" encoding="utf-8" ?>
<dwsync>
<file name="DB.php" server="172.17.1.50//var/www/html/CallCenter/" local="129582683540000000" remote="129773958830000000" />
<file name="DB_active_rec.php" server="172.17.1.50//var/www/html/CallCenter/" local="129582683540000000" remote="129773958830000000" />
<file name="DB_cache.php" server="172.17.1.50//var/www/html/CallCenter/" local="129582683540000000" remote="129773958830000000" />
<file name="DB_driver.php" server="172.17.1.50//var/www/html/CallCenter/" local="129582683540000000" remote="129773958830000000" />
<file name="DB_forge.php" server="172.17.1.50//var/www/html/CallCenter/" local="129582683540000000" remote="129773958830000000" />
<file name="DB_result.php" server="172.17.1.50//var/www/html/CallCenter/" local="129582683540000000" remote="129773958840000000" />
<file name="DB_utility.php" server="172.17.1.50//var/www/html/CallCenter/" local="129582683540000000" remote="129773958840000000" />
<file name="index.html" server="172.17.1.50//var/www/html/CallCenter/" local="129582683540000000" remote="129773958850000000" />
<file name="DB.php" server="172.17.1.16//var/www/html/CallCenter/" local="130026204871621120" remote="130365712560000000" />
<file name="DB_active_rec.php" server="172.17.1.16//var/www/html/CallCenter/" local="130026204871621120" remote="130365712560000000" />
<file name="DB_cache.php" server="172.17.1.16//var/www/html/CallCenter/" local="130026204871621120" remote="130365712570000000" />
<file name="DB_driver.php" server="172.17.1.16//var/www/html/CallCenter/" local="130026204871621120" remote="130365712570000000" />
<file name="DB_forge.php" server="172.17.1.16//var/www/html/CallCenter/" local="130026204871621120" remote="130365712570000000" />
<file name="DB_result.php" server="172.17.1.16//var/www/html/CallCenter/" local="130026204871621120" remote="130365712570000000" />
<file name="DB_utility.php" server="172.17.1.16//var/www/html/CallCenter/" local="130026204871621120" remote="130365712580000000" />
<file name="index.html" server="172.17.1.16//var/www/html/CallCenter/" local="130026204871621120" remote="130365712650000000" />
<file name="DB.php" server="172.17.1.51//var/www/html/CallCenter/" local="129808491880000000" remote="129865747080000000" />
<file name="DB_active_rec.php" server="172.17.1.51//var/www/html/CallCenter/" local="129808491880000000" remote="129865747080000000" />
<file name="DB_cache.php" server="172.17.1.51//var/www/html/CallCenter/" local="129808491880000000" remote="129865747080000000" />
<file name="DB_driver.php" server="172.17.1.51//var/www/html/CallCenter/" local="129808491880000000" remote="129865747090000000" />
<file name="DB_forge.php" server="172.17.1.51//var/www/html/CallCenter/" local="129808491880000000" remote="129865747090000000" />
<file name="DB_result.php" server="172.17.1.51//var/www/html/CallCenter/" local="129808491880000000" remote="129865747090000000" />
<file name="DB_utility.php" server="172.17.1.51//var/www/html/CallCenter/" local="129808491880000000" remote="129865747090000000" />
<file name="index.html" server="172.17.1.51//var/www/html/CallCenter/" local="129808491900000000" remote="129865747130000000" />
<file name="DB.php" server="172.17.1.26//var/www/html/CallCenter/" local="129808491880000000" remote="130011561260000000" />
<file name="DB_active_rec.php" server="172.17.1.26//var/www/html/CallCenter/" local="129808491880000000" remote="130011561270000000" />
<file name="DB_cache.php" server="172.17.1.26//var/www/html/CallCenter/" local="129808491880000000" remote="130011561270000000" />
<file name="DB_driver.php" server="172.17.1.26//var/www/html/CallCenter/" local="129808491880000000" remote="130011561270000000" />
<file name="DB_forge.php" server="172.17.1.26//var/www/html/CallCenter/" local="129808491880000000" remote="130011561270000000" />
<file name="DB_result.php" server="172.17.1.26//var/www/html/CallCenter/" local="129808491880000000" remote="130011561280000000" />
<file name="DB_utility.php" server="172.17.1.26//var/www/html/CallCenter/" local="129808491880000000" remote="130011561280000000" />
<file name="index.html" server="172.17.1.26//var/www/html/CallCenter/" local="129808491900000000" remote="130011561320000000" />
<file name="DB.php" server="192.168.20.171//var/www/html/CallCenter/" local="130026204871621120" remote="130397723680000000" />
<file name="DB_active_rec.php" server="192.168.20.171//var/www/html/CallCenter/" local="130026204871621120" remote="130397723680000000" />
<file name="DB_cache.php" server="192.168.20.171//var/www/html/CallCenter/" local="130026204871621120" remote="130397723690000000" />
<file name="DB_driver.php" server="192.168.20.171//var/www/html/CallCenter/" local="130026204871621120" remote="130397723690000000" />
<file name="DB_forge.php" server="192.168.20.171//var/www/html/CallCenter/" local="130026204871621120" remote="130397723690000000" />
<file name="DB_result.php" server="192.168.20.171//var/www/html/CallCenter/" local="130026204871621120" remote="130397723690000000" />
<file name="DB_utility.php" server="192.168.20.171//var/www/html/CallCenter/" local="130026204871621120" remote="130397723690000000" />
<file name="index.html" server="192.168.20.171//var/www/html/CallCenter/" local="130026204871621120" remote="130397723710000000" />
<file name="DB.php" server="192.168.0.2//var/www/html/CallCenter/" local="130026204871621120" remote="130400179590000000" />
<file name="DB_active_rec.php" server="192.168.0.2//var/www/html/CallCenter/" local="130026204871621120" remote="130400179600000000" />
<file name="DB_cache.php" server="192.168.0.2//var/www/html/CallCenter/" local="130026204871621120" remote="130400179600000000" />
<file name="DB_driver.php" server="192.168.0.2//var/www/html/CallCenter/" local="130026204871621120" remote="130400179600000000" />
<file name="DB_forge.php" server="192.168.0.2//var/www/html/CallCenter/" local="130026204871621120" remote="130400179600000000" />
<file name="DB_result.php" server="192.168.0.2//var/www/html/CallCenter/" local="130026204871621120" remote="130400179600000000" />
<file name="DB_utility.php" server="192.168.0.2//var/www/html/CallCenter/" local="130026204871621120" remote="130400179600000000" />
<file name="index.html" server="192.168.0.2//var/www/html/CallCenter/" local="130026204871621120" remote="130400179620000000" />
<file name="DB.php" server="172.17.1.11//var/www/html/CallCenter/" local="130026204871621120" remote="130406187420000000" />
<file name="DB_active_rec.php" server="172.17.1.11//var/www/html/CallCenter/" local="130026204871621120" remote="130406187420000000" />
<file name="DB_cache.php" server="172.17.1.11//var/www/html/CallCenter/" local="130026204871621120" remote="130406187420000000" />
<file name="DB_driver.php" server="172.17.1.11//var/www/html/CallCenter/" local="130026204871621120" remote="130406187420000000" />
<file name="DB_forge.php" server="172.17.1.11//var/www/html/CallCenter/" local="130026204871621120" remote="130406187420000000" />
<file name="DB_result.php" server="172.17.1.11//var/www/html/CallCenter/" local="130026204871621120" remote="130406187420000000" />
<file name="DB_utility.php" server="172.17.1.11//var/www/html/CallCenter/" local="130026204871621120" remote="130406187420000000" />
<file name="index.html" server="172.17.1.11//var/www/html/CallCenter/" local="130026204871621120" remote="130406187440000000" />
</dwsync>