<?xml version="1.0" encoding="utf-8" ?>
<dwsync>
<file name="1.html" server="172.17.1.21//var/www/html/CallCenter/" local="129577675240000000" remote="129676360290000000" />
<file name="2.html" server="172.17.1.21//var/www/html/CallCenter/" local="129577675240000000" remote="129676360290000000" />
<file name="3.html" server="172.17.1.21//var/www/html/CallCenter/" local="129577675240000000" remote="129676360290000000" />
<file name="1.html" server="172.17.1.50//var/www/html/CallCenter/" local="129577675240000000" remote="129773958810000000" />
<file name="2.html" server="172.17.1.50//var/www/html/CallCenter/" local="129577675240000000" remote="129773958820000000" />
<file name="3.html" server="172.17.1.50//var/www/html/CallCenter/" local="129577675240000000" remote="129773958820000000" />
<file name="1.html" server="172.17.1.16//var/www/html/CallCenter/" local="129808491860000000" remote="129993201460000000" />
<file name="2.html" server="172.17.1.16//var/www/html/CallCenter/" local="129808491860000000" remote="129993201460000000" />
<file name="3.html" server="172.17.1.16//var/www/html/CallCenter/" local="129808491860000000" remote="129993201460000000" />
<file name="1.html" server="172.17.1.51//var/www/html/CallCenter/" local="129808491860000000" remote="129865747040000000" />
<file name="2.html" server="172.17.1.51//var/www/html/CallCenter/" local="129808491860000000" remote="129865747040000000" />
<file name="3.html" server="172.17.1.51//var/www/html/CallCenter/" local="129808491860000000" remote="129865747040000000" />
<file name="1.html" server="172.17.1.26//var/www/html/CallCenter/" local="129808491860000000" remote="130011561230000000" />
<file name="2.html" server="172.17.1.26//var/www/html/CallCenter/" local="129808491860000000" remote="130011561230000000" />
<file name="3.html" server="172.17.1.26//var/www/html/CallCenter/" local="129808491860000000" remote="130011561230000000" />
</dwsync>